smshelper/__init__.py
smshelper/smshelper.py
smshelper/tests/__init__.py
smshelper/tests/test_sms_helper.py
smshelper-0.1.5.dist-info/METADATA
smshelper-0.1.5.dist-info/RECORD
smshelper-0.1.5.dist-info/WHEEL
smshelper-0.1.5.dist-info/top_level.txt
