Metadata-Version: 2.1
Name: smshelper
Version: 0.1.5
Summary: SMS helper and tool
Home-page: https://github.com/jaygel179/smshelper
Author: Elpedio Adoptante Jr
Author-email: adoptante.elpedio@gmail.com
License: UNKNOWN
Platform: UNKNOWN
Classifier: Programming Language :: Python :: 2.7
Classifier: License :: OSI Approved :: MIT License
Classifier: Operating System :: OS Independent
